rlapis/__init__.py
rlapis/gym_spaces_types.py
rlapis/gym_spaces_types_errors.py
tests/__init__.py
tests/test_gym_spaces_types.py
rlapis-0.0.1.dist-info/METADATA
rlapis-0.0.1.dist-info/WHEEL
rlapis-0.0.1.dist-info/top_level.txt
rlapis-0.0.1.dist-info/RECORD
